zxing/__init__.py
zxing/__main__.py
zxing/version.py
zxing/java/core.jar
zxing/java/javase.jar
zxing/java/jcommander.jar
zxing-1.0.1.dist-info/LICENSE
zxing-1.0.1.dist-info/METADATA
zxing-1.0.1.dist-info/WHEEL
zxing-1.0.1.dist-info/entry_points.txt
zxing-1.0.1.dist-info/top_level.txt
zxing-1.0.1.dist-info/RECORD
