Metadata-Version: 2.1
Name: zxing
Version: 1.0.1
Summary: Wrapper for decoding/reading barcodes with ZXing (Zebra Crossing) library
Home-page: https://github.com/dlenski/python-zxing
Author: Daniel Lenski
Author-email: dlenski@gmail.com
License: LGPL v3 or later
Classifier: Development Status :: 4 - Beta
Classifier: Intended Audience :: Developers
Classifier: License :: OSI Approved :: GNU Lesser General Public License v3 or later (LGPLv3+)
Classifier: Topic :: Multimedia :: Graphics :: Capture
Classifier: Topic :: Scientific/Engineering :: Image Recognition
Classifier: Topic :: Software Development :: Libraries :: Java Libraries
Classifier: Topic :: Software Development :: Libraries :: Python Modules
Classifier: Topic :: Utilities
Classifier: Programming Language :: Python :: 3.6
Classifier: Programming Language :: Python :: 3.7
Classifier: Programming Language :: Python :: 3.8
Classifier: Programming Language :: Python :: 3.9
Classifier: Programming Language :: Python :: 3.10
Classifier: Programming Language :: Python :: 3.11
Requires-Python: >=3
License-File: LICENSE
Provides-Extra: image
Requires-Dist: pillow<6.0,>=3.0; python_version < "3.5" and extra == "image"
Requires-Dist: pillow<8.0,>=3.0; (python_version >= "3.5" and python_version < "3.6") and extra == "image"
Requires-Dist: pillow>=8.0; python_version >= "3.6" and extra == "image"
